rtl/fa.sv
/* 
* Author: Ryan Cramer
* Date: Oct 19, 2025
* Design: Full-Adder
*
* Description:
* A full adder that takes in 3 inputs, cin, a, and b
* and gives two outputs: sum, and co
*/

`timescale 1ns/1ps

module fa (
	input a,
	input b,
	input cin,
	output logic sum,
	output logic co
);

	assign sum = a ^ b ^ cin;
	assign co = (a&b)|(cin&(a^b));

endmodule

sim/tb_fa/tb_fa.sv
`timescale 1ns/1ps

module tb_fa();

	logic a, b, cin;
	
	fa DUT(
		.a(a),
		.b(b),
		.cin(cin),
		.sum(),
		.co()
	);
	
	initial begin
		$dumpfile("tb_fa.vcd");
		$dumpvars(0, tb_fa);
	end

	always begin
		// test all zeroes
		#10 a <= 1'b0;
			b <= 1'b0;
			cin <= 1'b0;
		
		//assert(DUT.sum == 1'b0);
		//assert(DUT.co == 1'b0);
		
		// test a high
		#10 a <= 1'b1;
			b <= 1'b0;
			cin <= 1'b0;
		
		//assert(DUT.sum == 1'b1);
		//assert(DUT.co == 1'b0);
	
		// test b high
		#10 a <= 1'b0;
			b <= 1'b1;
			cin <= 1'b0;
		
		//assert(DUT.sum == 1'b1);
		//assert(DUT.co == 1'b0);

		// test cin high
		#10 a <= 1'b0;
			b <= 1'b0;
			cin <= 1'b1;
		
		//assert(DUT.sum == 1'b1);
		//assert(DUT.co == 1'b0);

		// test a + b = co high
		#10 a <= 1'b1;
			b <= 1'b1;
			cin <= 1'b0;
		
		//assert(DUT.sum == 1'b0);
		//assert(DUT.co == 1'b1);

		// test a + cin = co high
		#10 a <= 1'b1;
			b <= 1'b0;
			cin <= 1'b1;
		
		//assert(DUT.sum == 1'b0);
		//assert(DUT.co == 1'b1);

		// test b + cin = co high
		#10 a <= 1'b0;
			b <= 1'b1;
			cin <= 1'b1;
		
		//assert(DUT.sum == 1'b0);
		//assert(DUT.co == 1'b1);

		#10 a <= 1'b1;
			b <= 1'b1;
			cin <= 1'b1;
		
		//assert(DUT.sum == 1'b1);
		//assert(DUT.co == 1'b1);

		#10 $finish;

	end

endmodule

sim/tb_fa/tb_fa.vcd
$version Generated by VerilatedVcd $end
$timescale 1ps $end
 $scope module $rootio $end
 $upscope $end
 $scope module tb_fa $end
  $var wire 1 # a $end
  $var wire 1 $ b $end
  $var wire 1 % cin $end
  $scope module DUT $end
   $var wire 1 # a $end
   $var wire 1 $ b $end
   $var wire 1 % cin $end
   $var wire 1 & sum $end
   $var wire 1 ' co $end
  $upscope $end
 $upscope $end
$enddefinitions $end


#0
0#
0$
0%
0&
0'
#10000
#20000
1#
1&
#30000
0#
1$
#40000
0$
1%
#50000
1#
1$
0%
0&
1'
#60000
0$
1%
#70000
0#
1$
#80000
1#
1&
